RashSetup/__init__.py
RashSetup/drivers.py
RashSetup/register.py
RashSetup/utils.py
rashsetup-1.6.3.dist-info/WHEEL
rashsetup-1.6.3.dist-info/METADATA
rashsetup-1.6.3.dist-info/RECORD
