Metadata-Version: 2.1
Name: rashsetup
Version: 1.6.3
Summary: RashSetup sets up Some RashThings for us
License: MIT
Author: RahulARanger
Author-email: saihanumarahul66@gmail.com
Requires-Python: >=3.8,<4.0
Classifier: License :: OSI Approved :: MIT License
Classifier: Programming Language :: Python :: 3
Classifier: Programming Language :: Python :: 3.8
Classifier: Programming Language :: Python :: 3.9
Requires-Dist: selenium (==4.1.0)
Requires-Dist: webdriver_manager (==3.5.2)
